{
    "properties": {
        "roleName": "VM Read and RunCommand Role",
        "description": "This role can read VM objects and use the RunCommand action",
        "assignableScopes": [
            "/"
        ],
        "permissions": [
            {
                "actions": [
                    "Microsoft.Compute/virtualMachines/runCommand/action",
                    "Microsoft.Compute/virtualMachines/read"
                ],
                "notActions": [],
                "dataActions": [],
                "notDataActions": []
            }
        ]
    }
}